neobuilder/__init__.py
neobuilder/cli/__init__.py
neobuilder/cli/neobuilder.py
neobuilder/data/templates/dataclass.jinja2
neobuilder/data/templates/dataclass_module.jinja2
neobuilder/data/templates/grpc_receiver.jinja2
neobuilder/data/templates/grpc_sender.jinja2
neobuilder/data/templates/init.jinja2
neobuilder/data/templates/interface.jinja2
neobuilder/data/templates/root_init.jinja2
neobuilder/data/templates/macros/indentclude.jinja2
neobuilder/data/templates/parts/_enum_map.jinja2
neobuilder/data/templates/parts/_interface_method.jinja2
neobuilder/data/templates/parts/_interface_service.jinja2
neobuilder/data/templates/parts/_nested_messages.jinja2
neobuilder/descwrap/__init__.py
neobuilder/descwrap/_field.py
neobuilder/descwrap/_method.py
neobuilder/generators/__init__.py
neobuilder/generators/servicebuilders/__init__.py
neobuilder/generators/servicebuilders/base.py
neobuilder/generators/servicebuilders/grpc_receiver.py
neobuilder/generators/servicebuilders/grpc_sender.py
neobuilder/generators/servicebuilders/grpc_server.py
neobuilder/generators/servicebuilders/implementation.py
neobuilder/generators/servicebuilders/interface.py
neobuilder/generators/symbols/__init__.py
neobuilder/generators/symbols/common.py
neobuilder/generators/symbols/dataclass.py
neobuilder/generators/symbols/modules.py
neobuilder/generators/symbols/service.py
neobuilder/neobuilder/__init__.py
neobuilder/neobuilder/render/__init__.py
neobuilder/neobuilder/render/renderer.py
neobuilder/structs/__init__.py
neobuilder/structs/_base.py
neobuilder/structs/protofile.py
neobuilder/structs/pytype.py
neobuilder-5.3.1.dist-info/LICENSE
neobuilder-5.3.1.dist-info/METADATA
neobuilder-5.3.1.dist-info/WHEEL
neobuilder-5.3.1.dist-info/entry_points.txt
neobuilder-5.3.1.dist-info/top_level.txt
neobuilder-5.3.1.dist-info/RECORD
