Metadata-Version: 2.1
Name: neobuilder
Version: 5.3.1
Summary: Builds Neobuf Packages from Protobuf files using Protoplasm! :D
Author-email: Thordur Matthiasson <thordurm@ccpgames.com>
License: MIT License
Project-URL: Homepage, https://github.com/ccpgames/neobuilder
Project-URL: Documentation, https://github.com/ccpgames/neobuilder/blob/main/README.md
Project-URL: Repository, https://github.com/ccpgames/neobuilder.git
Project-URL: Issues, https://github.com/ccpgames/neobuilder/issues
Project-URL: Changelog, https://github.com/ccpgames/neobuilder/blob/main/CHANGELOG.md
Keywords: protobuf,proto,protoplasm,dataclasses,tools,ccp,utils
Classifier: Development Status :: 5 - Production/Stable
Classifier: License :: OSI Approved :: MIT License
Classifier: Intended Audience :: Developers
Classifier: Programming Language :: Python
Classifier: Programming Language :: Python :: 3
Classifier: Programming Language :: Python :: 3.8
Classifier: Programming Language :: Python :: 3.9
Classifier: Programming Language :: Python :: 3.10
Classifier: Programming Language :: Python :: 3.11
Classifier: Programming Language :: Python :: 3.12
Classifier: Topic :: Software Development
Classifier: Topic :: Software Development :: Libraries
Classifier: Topic :: Software Development :: Libraries :: Python Modules
Classifier: Topic :: Utilities
License-File: LICENSE
Requires-Dist: protoplasm<6,>=5.2
Requires-Dist: ccptools<2,>=1.1
Requires-Dist: Jinja2<4,>=3.1
Requires-Dist: semver<4,>=3.0.2
